colorarise/__init__.py
colorarise/color.py
colorarise-0.0.1.dist-info/LICENSE
colorarise-0.0.1.dist-info/METADATA
colorarise-0.0.1.dist-info/WHEEL
colorarise-0.0.1.dist-info/top_level.txt
colorarise-0.0.1.dist-info/RECORD
