Metadata-Version: 2.1
Name: colorarise
Version: 0.0.1
Summary: python package to handle colorful outputs
Home-page: https://github.com/Falldog/pyconcrete
Author: James root
Author-email: rapid7dev123@gmail.com
Classifier: Programming Language :: Python :: 3
Classifier: License :: OSI Approved :: MIT License
Classifier: Operating System :: OS Independent
Requires-Python: >=3.7
License-File: LICENSE
